GRAIL/Correlation.py
GRAIL/Correlation_protocol.py
GRAIL/DistanceMatrix.py
GRAIL/FrequentDirections.py
GRAIL/GRAIL_core.py
GRAIL/OPQ.py
GRAIL/PQ.py
GRAIL/Representation.py
GRAIL/SINK.py
GRAIL/TimeSeries.py
GRAIL/__init__.py
GRAIL/exceptions.py
GRAIL/kNN.py
GRAIL/kernels.py
GRAIL/kshape.py
grailts-0.1.0.dist-info/METADATA
grailts-0.1.0.dist-info/WHEEL
grailts-0.1.0.dist-info/top_level.txt
grailts-0.1.0.dist-info/RECORD
