Metadata-Version: 2.1
Name: grailts
Version: 0.1.0
Summary: Python implementation of GRAIL
Home-page: https://github.com/johnpaparrizos/GRAIL
Author: Karhan Kaan Kayan
Author-email: kayankarhankaan@gmail.com
License: UNKNOWN
Project-URL: Bug Tracker, https://github.com/johnpaparrizos/GRAIL/issues
Platform: UNKNOWN
Classifier: Programming Language :: Python :: 3
Classifier: License :: Other/Proprietary License
Classifier: Operating System :: OS Independent
Requires-Python: >=3.6
Requires-Dist: numpy
Requires-Dist: scipy
Requires-Dist: tslearn
